pytherm.py
setup.py
pytherm.egg-info/PKG-INFO
pytherm.egg-info/SOURCES.txt
pytherm.egg-info/dependency_links.txt
pytherm.egg-info/top_level.txt