Metadata-Version: 1.0
Name: pytherm
Version: 0.0.1
Summary: Pytherm project
Home-page: UNKNOWN
Author: Dong-Kwon Kim
Author-email: UNKNOWN
License: UNKNOWN
Platform: UNKNOWN
